LICENSE
MANIFEST.in
README.md
requirements.txt
setup.cfg
setup.py
attributes/__init__.py
attributes/constants.py
attributes/defaults.py
attributes/forms.py
attributes/managers.py
attributes/querysets.py
attributes/settings.py
attributes/translation.py
attributes/utils.py
attributes/admin/__init__.py
attributes/admin/forms.py
attributes/locale/ru/LC_MESSAGES/django.mo
attributes/locale/ru/LC_MESSAGES/django.po
attributes/locale/uk/LC_MESSAGES/django.mo
attributes/locale/uk/LC_MESSAGES/django.po
attributes/migrations/0001_initial.py
attributes/migrations/__init__.py
attributes/models/__init__.py
attributes/models/attribute.py
attributes/models/attribute_option.py
attributes/models/attribute_value.py
django_mp_shop_attrs.egg-info/PKG-INFO
django_mp_shop_attrs.egg-info/SOURCES.txt
django_mp_shop_attrs.egg-info/dependency_links.txt
django_mp_shop_attrs.egg-info/requires.txt
django_mp_shop_attrs.egg-info/top_level.txt