Metadata-Version: 1.1
Name: django-mp-shop-attrs
Version: 2.0
Summary: Django attributes apps
Home-page: https://github.com/pmaigutyak/mp-shop-attrs
Author: Paul Maigutyak
Author-email: pmaigutyak@gmail.com
License: MIT
Download-URL: https://github.com/pmaigutyak/mp-shop-attrs/archive/2.0.tar.gz
Platform: UNKNOWN
